{
  "initial:before": {
    "loopback#favicon": {}
  },
  "initial": {
    "compression": {},
    "cors": {
      "params": {
        "origin": true,
        "credentials": true,
        "maxAge": 86400
      }
    },
    "./middleware/request-logging#requestLogging": {}
  },
  "validateRequest": { 
     "./middleware/request-validator": {
       "paths":"/api/service/v1/opportunity"
      }
  },
  "session": {},
  "auth": {},
  "parse": {},
  "routes": {},
  "files": {},
  "final": {
    "loopback#urlNotFound": {}
  },
  "final:after": {
    "errorhandler": {}
  }
}
